easysocket/__init__.py
easysocket/core.py
easysocket/adapters/__init__.py
easysocket/adapters/django_adapter.py
easysocket/adapters/flask_adapter.py
easysocket/protocols/__init__.py
easysocket/protocols/socketio.py
easysocket/protocols/websocket.py
easysocket_nishant4i-0.1.3.dist-info/LICENSE
easysocket_nishant4i-0.1.3.dist-info/METADATA
easysocket_nishant4i-0.1.3.dist-info/WHEEL
easysocket_nishant4i-0.1.3.dist-info/top_level.txt
easysocket_nishant4i-0.1.3.dist-info/RECORD
